chi2sim/__init__.py
chi2sim/chi2_cont_sim.c
chi2sim/chi2_cont_sim.cp311-win_amd64.pyd
chi2sim/chi2_cont_sim.pyx
chi2sim/src/chi_square_mc.c
chi2sim/src/chi_square_mc.h
chi2sim-1.1.1.dist-info/METADATA
chi2sim-1.1.1.dist-info/WHEEL
chi2sim-1.1.1.dist-info/top_level.txt
chi2sim-1.1.1.dist-info/RECORD
