Metadata-Version: 2.1
Name: chi2sim
Version: 1.1.1
Summary: Chi-square test with Monte Carlo simulation
Author-email: Your Name <your.email@example.com>
Project-URL: Homepage, https://github.com/kisha126/chi2sim
Project-URL: Bug Tracker, https://github.com/kisha126/chi2sim/issues
Project-URL: Documentation, https://github.com/kisha126/chi2sim#readme
Keywords: statistics,chi-square,monte-carlo,simulation
Classifier: Programming Language :: Python :: 3
Classifier: License :: OSI Approved :: MIT License
Classifier: Operating System :: OS Independent
Classifier: Topic :: Scientific/Engineering :: Mathematics
Requires-Python: >=3.7
Requires-Dist: numpy>=1.19.2
